caleginfo/__init__.py
caleginfo/ca_leginfo.py
caleginfo/ca_leginfo_integration_test.py
caleginfo/constants.py
caleginfo-0.0.3.dist-info/METADATA
caleginfo-0.0.3.dist-info/WHEEL
caleginfo-0.0.3.dist-info/licenses/LICENSE
caleginfo-0.0.3.dist-info/RECORD
