Metadata-Version: 2.4
Name: CALegInfo
Version: 0.0.3
Summary: An API for interacting with CA Legislative Information at https://leginfo.legislature.ca.gov
Project-URL: Homepage, https://github.com/mbernico/ca_leginfo_api
Project-URL: Issues, https://github.com/mbernico/ca_leginfo_api
Author-email: Mike Bernico <mike.bernico@gmail.com>
License: Apache2
License-File: LICENSE
Classifier: Operating System :: OS Independent
Classifier: Programming Language :: Python :: 3
Requires-Python: >=3.8
Requires-Dist: beautifulsoup4
Requires-Dist: requests
